cardboard/Exceptions.py
cardboard/__init__.py
cardboard/cardboard.py
cardboard/cardboard_async.py
cardboard/flask_integration.py
cardboard/quart_integration.py
cardboard.py-0.0.24.dist-info/METADATA
cardboard.py-0.0.24.dist-info/WHEEL
cardboard.py-0.0.24.dist-info/top_level.txt
cardboard.py-0.0.24.dist-info/RECORD
