Metadata-Version: 2.1
Name: cardboard.py
Version: 0.0.24
Summary: Official API wrapper for https://cardboard.ink/api/v1/
Home-page: https://github.com/cardboard-ink/cardboard.py/
Author: YumYummity
Author-email: 034nop@gmail.com
Classifier: Development Status :: 5 - Production/Stable
Classifier: Intended Audience :: Developers
Classifier: License :: OSI Approved :: MIT License
Classifier: Programming Language :: Python
Classifier: Programming Language :: Python :: 3
Classifier: Programming Language :: Python :: 3.9
Classifier: Programming Language :: Python :: 3.10
Classifier: Programming Language :: Python :: 3.11
Classifier: Topic :: Software Development :: Libraries :: Python Modules
Classifier: Topic :: Internet :: WWW/HTTP
Requires-Python: >=3.9
Requires-Dist: requests
Requires-Dist: aiohttp
Requires-Dist: python-dateutil
Provides-Extra: flask
Requires-Dist: Flask ; extra == 'flask'
Provides-Extra: quart
Requires-Dist: Quart ; extra == 'quart'
